odoo/addons/pos_event_sale_session/README.rst
odoo/addons/pos_event_sale_session/__init__.py
odoo/addons/pos_event_sale_session/__manifest__.py
odoo/addons/pos_event_sale_session/i18n/es.po
odoo/addons/pos_event_sale_session/i18n/fr.po
odoo/addons/pos_event_sale_session/i18n/it.po
odoo/addons/pos_event_sale_session/i18n/pos_event_sale_session.pot
odoo/addons/pos_event_sale_session/models/__init__.py
odoo/addons/pos_event_sale_session/models/event_session.py
odoo/addons/pos_event_sale_session/models/pos_order_line.py
odoo/addons/pos_event_sale_session/readme/CONTRIBUTORS.rst
odoo/addons/pos_event_sale_session/readme/DESCRIPTION.rst
odoo/addons/pos_event_sale_session/reports/__init__.py
odoo/addons/pos_event_sale_session/reports/report_pos_order.py
odoo/addons/pos_event_sale_session/reports/report_pos_order.xml
odoo/addons/pos_event_sale_session/static/description/icon.png
odoo/addons/pos_event_sale_session/static/description/index.html
odoo/addons/pos_event_sale_session/static/src/js/db.js
odoo/addons/pos_event_sale_session/static/src/js/models.js
odoo/addons/pos_event_sale_session/static/src/js/Popups/EventSelectorPopup/EventItem.js
odoo/addons/pos_event_sale_session/static/src/js/Popups/EventSelectorPopup/EventSelectorPopup.js
odoo/addons/pos_event_sale_session/static/src/js/Popups/EventTicketsPopup/EventTicketItem.js
odoo/addons/pos_event_sale_session/static/src/js/Popups/EventTicketsPopup/EventTicketsPopup.js
odoo/addons/pos_event_sale_session/static/src/js/Screens/EventRegistrationReceipt.js
odoo/addons/pos_event_sale_session/static/src/js/Screens/TicketScreen.js
odoo/addons/pos_event_sale_session/static/src/js/models/EventEvent.js
odoo/addons/pos_event_sale_session/static/src/js/models/EventSession.js
odoo/addons/pos_event_sale_session/static/src/js/models/Order.js
odoo/addons/pos_event_sale_session/static/src/js/models/Orderline.js
odoo/addons/pos_event_sale_session/static/src/js/models/PosModel.js
odoo_addon_pos_event_sale_session-15.0.3.0.0.5.dist-info/METADATA
odoo_addon_pos_event_sale_session-15.0.3.0.0.5.dist-info/WHEEL
odoo_addon_pos_event_sale_session-15.0.3.0.0.5.dist-info/top_level.txt
odoo_addon_pos_event_sale_session-15.0.3.0.0.5.dist-info/RECORD
