Metadata-Version: 2.1
Name: odoo-addon-pos-event-sale-session
Version: 15.0.3.0.0.5
Summary: Sell event sessions from Point of Sale
Home-page: https://github.com/OCA/pos
Author: Moka Tourisme, Odoo Community Association (OCA)
Author-email: support@odoo-community.org
License: AGPL-3
Platform: UNKNOWN
Classifier: Programming Language :: Python
Classifier: Framework :: Odoo
Classifier: Framework :: Odoo :: 15.0
Classifier: License :: OSI Approved :: GNU Affero General Public License v3
Requires-Python: >=3.8
Requires-Dist: odoo-addon-event-sale-session <15.1dev,>=15.0dev
Requires-Dist: odoo-addon-pos-event-sale <15.1dev,>=15.0dev
Requires-Dist: odoo <15.1dev,>=15.0a
